apeman/__init__.py
apeman/model/__init__.py
apeman/model/model_category_pb2.py
apeman/model/model_category_pb2_grpc.py
apeman/model/model_instance_dto_pb2.py
apeman/model/model_instance_dto_pb2_grpc.py
apeman/model/model_instance_task_dto_pb2.py
apeman/model/model_instance_task_dto_pb2_grpc.py
apeman/model/model_instance_task_launch_type_pb2.py
apeman/model/model_instance_task_launch_type_pb2_grpc.py
apeman/model/model_instance_task_status_pb2.py
apeman/model/model_instance_task_status_pb2_grpc.py
apeman/model/model_instance_task_type_pb2.py
apeman/model/model_instance_task_type_pb2_grpc.py
apeman/model/openapi/__init__.py
apeman/model/openapi/apeman_open_api.py
apeman/model/openapi/apeman_open_api_pb2.py
apeman/model/openapi/apeman_open_api_pb2_grpc.py
apeman/model/openapi/apeman_open_api_test.py
apeman/model/openapi/model_instance_task_launch_type.py
apeman/model/openapi/model_instance_task_status.py
apeman/model/openapi/model_instance_task_type.py
apeman/model/openapi/mockserver/__init__.py
apeman/model/openapi/mockserver/apeman_model_server.py
apeman_model_client-0.2.7.5.dist-info/METADATA
apeman_model_client-0.2.7.5.dist-info/WHEEL
apeman_model_client-0.2.7.5.dist-info/top_level.txt
apeman_model_client-0.2.7.5.dist-info/RECORD
